{
	"configurations" : 
	[
		{
			"directories" : 
			[
				{
					"build" : ".",
					"jsonFile" : "directory-.-Release-f5ebdc15457944623624.json",
					"minimumCMakeVersion" : 
					{
						"string" : "3.7"
					},
					"projectIndex" : 0,
					"source" : ".",
					"targetIndexes" : 
					[
						0
					]
				}
			],
			"name" : "Release",
			"projects" : 
			[
				{
					"directoryIndexes" : 
					[
						0
					],
					"name" : "SV-file",
					"targetIndexes" : 
					[
						0
					]
				}
			],
			"targets" : 
			[
				{
					"directoryIndex" : 0,
					"id" : "SV-file::@6890427a1f51a3e7e1df",
					"jsonFile" : "target-SV-file-Release-58a7bced72bed58751e6.json",
					"name" : "SV-file",
					"projectIndex" : 0
				}
			]
		}
	],
	"kind" : "codemodel",
	"paths" : 
	{
		"build" : "/home/nathan/repos/SV/src/build/Release",
		"source" : "/home/nathan/repos/SV/src"
	},
	"version" : 
	{
		"major" : 2,
		"minor" : 6
	}
}
